pyupgradecheck/__init__.py
pyupgradecheck/checker.py
pyupgradecheck/cli.py
pyupgradecheck-0.1.7.dist-info/licenses/LICENSE
pyupgradecheck-0.1.7.dist-info/METADATA
pyupgradecheck-0.1.7.dist-info/WHEEL
pyupgradecheck-0.1.7.dist-info/entry_points.txt
pyupgradecheck-0.1.7.dist-info/top_level.txt
pyupgradecheck-0.1.7.dist-info/RECORD
