Metadata-Version: 2.4
Name: pyupgradecheck
Version: 0.1.7
Summary: Check your installed Python packages for version compatibility
Author-email: Tammy DiPrima <tdiprima@yahoo.com>
License-Expression: MIT
Keywords: python,compatibility,pypi,upgrade,cli,dependency
Classifier: Topic :: Software Development :: Libraries :: Python Modules
Classifier: Topic :: Utilities
Classifier: Programming Language :: Python :: 3
Classifier: Intended Audience :: Developers
Classifier: Environment :: Console
Requires-Python: >=3.9
License-File: LICENSE
Requires-Dist: packaging
Requires-Dist: halo
Requires-Dist: httpx
Dynamic: license-file
